{
    "stockcode": "$TPGC",
    "bursacode": "7113",
    "bloomberg": "TOPG:MK",
    "alias": "TOPGLOV",
    "name": "TOP GLOVE CORP",
    "sdate": "2024-10-04",
    "stime": "08:59",
    "netchange": "0.000",
    "percentchange": "0.000%",
    "close": "1.01",
    "high": "1.02",
    "last": "1.010",
    "low": "1.00",
    "open": "1.01",
    "volume": "9938300",
    "yield": "35.45%",
    "bqos": "0.000",
    "pqos": "RT",
    "concreteservice": "IDN_FD3",
    "type": "0",
    "recstatus": "0",
    "modifieddate": "-",
    "earnings": "-0.065",
    "cfyield": "35.450",
    "peratio": "0.00",
    "exdivdate": "-",
    "dividend": "0.00",
    "turnover": "10,017,766.00",
    "mktvalue": "8,292.929",
    "tick": "up",
    "asksize": "988800",
    "bidsize": "2455100",
    "ask": "1.010",
    "bid": "1.000",
    "srreportdate": "2024-08-02",
    "srscoredate": "2024-07-28",
    "srscoreanalyst": "3",
    "srscorefund": "1",
    "srscorerv": "1",
    "srscorerisk": "4",
    "srscoretech": "7",
    "srscoreavg": "2",
    "srscorerectxt": "Hold",
    "srscorereccnt": "20",
    "dividendtp": "C",
    "divpaydate": "1970-01-01",
    "yrhigh": "1.31",
    "yrlow": "0.70",
    "yrhighdate": "2024-05-16",
    "yrlowdate": "2024-03-15",
    "lotsize": "100",
    "currency": "MYR",
    "shariah": "1",
    "price": "",
    "midcap": "0",
    "generaladdlink": "generalAddToWatchlist('TPGC.KL', 'TOP GLOVE CORP')",
    "board": "",
    "srscorerectxt_css": "ana_yellow ana_yellow_line",
    "tixstockpricebox_css": "noChgBox",
    "tixstockpchg_css": "txt_nochg",
    "tixstockarrowind_css": "arrowNochg",
    "tixstockavgscorecolor_css": "alf_grey",
    "tixstockern_css": "alf_yellow",
    "tixstockfnd_css": "alf_grey",
    "tixstockval_css": "alf_grey",
    "tixstockrsk_css": "alf_yellow",
    "tixstockmom_css": "alf_grey",
    "reuters": "TPGC.KL",
    "bidask": "1.000 & 1.010",
    "economicsectorcode": "Healthcare",
    "industrygroupcode": "Healthcare Equipment & Supplies",
    "recommend": {
        "stockcode": "TPGC.KL",
        "age": "Current",
        "unverifiedmean": "3.000",
        "preliminarymean": "3.000",
        "mean": "3.00",
        "high": "1.00",
        "low": "5.00",
        "numberofrecommendations": "18",
        "recommendation1": "2",
        "recommendation2": "5",
        "recommendation3": "4",
        "recommendation4": "5",
        "recommendation5": "2",
        "recommendationdate": "20 Jun 2024",
        "recommendationstatus": "hold",
        "difference": 1.99
    },
    "finrec": {
        "stockcode": "TPGC.KL",
        "marketcapitalization": "8,292.930",
        "totaldebtcapital": "617.732",
        "cashandequivalents": "948.466",
        "currententerprisevalue": "7,962.195",
        "currentevebitda": "9.438",
        "currentevrevenue": "3.634",
        "currentpe": "28.952",
        "currentpeexextraordinaryitems": "28.952",
        "pricetocashflow": "10.623",
        "pricetotangiblebook": "1.650",
        "dividendpayoutrate": "42.605",
        "currpricerevshr": "3.674",
        "currepexclextraltm": "0.000",
        "currpenormalizedlfy": "26.625",
        "pricetobook": "1.373",
        "pricetoearnings": "0.00",
        "bookvalue": "1.408",
        "lfy": "42.605",
        "lfi": "0.000"
    },
    "finshr": {
        "stockcode": "TPGC.KL",
        "revenue": "0.282",
        "eps": "-0.116",
        "epsbasic": "-0.116",
        "epsnormalized": "-0.083",
        "cashflow": "-0.068",
        "cashpershare": "0.118",
        "epsexclextra": "-0.116",
        "bkvalshrtoteqty": "0.736",
        "tangbkvaluetoteqty": "0.628"
    },
    "finpricevol": {
        "stockcode": "TPGC.KL",
        "oneyearchange": "28.66",
        "ytdchange": "12.22",
        "wkhigh52": "1.31",
        "wklow52": "0.70"
    },
    "finincome": {
        "stockcode": "TPGC.KL",
        "profit": "-473.226"
    },
    "fineffective": {
        "stockcode": "TPGC.KL",
        "roe": "-8.550",
        "roa": "-6.584"
    },
    "findividend": {
        "stockcode": "TPGC.KL",
        "dividendyield": "0.00",
        "dividend5year": "0.10",
        "dividendmostrecent": "0.00",
        "currentdividendyield": "0.00",
        "dividendyield5yearaverage": "0.147",
        "dividendpaydate": "2022-01-10",
        "dividendexdate": "2021-12-24",
        "annoucementdate": "2021-12-27",
        "dividendquarterlydeclared": "0.012"
    },
    "businesssummary": "Top Glove Corporation Bhd. is a Malaysia-based manufacturer of gloves. The Company offers a comprehensive product range that extends beyond gloves and includes products, such as dental dams, exercise bands, latex sheets, tourniquets, condoms and face..."
}